resource_pack/__init__.py
resource_pack/functions.py
resource_pack/resource_manager.py
py_resource_pack-0.3.0.dist-info/LICENSE
py_resource_pack-0.3.0.dist-info/WHEEL
py_resource_pack-0.3.0.dist-info/METADATA
py_resource_pack-0.3.0.dist-info/RECORD
